pcfg/__init__.py
pcfg/pcfg.py
pcfg-0.1.5.dist-info/LICENSE
pcfg-0.1.5.dist-info/WHEEL
pcfg-0.1.5.dist-info/METADATA
pcfg-0.1.5.dist-info/RECORD
